["hydra_opt_2806",{"summary":{"iterations":5,"stop_reason":{"Other":"Found equivalence"},"egraph_nodes":189,"egraph_classes":101,"memo_size":231,"rebuilds":20,"total_time":0.0011109140000000002,"search_time":0.000425014,"apply_time":0.000642816,"rebuild_time":0.000041958999999999996},"crude_time":0.00375041,"iteration_info":[{"egraph_nodes":18,"egraph_classes":17,"applied":{"reduce_mod_bis":3,"sel_def":2,"not_bw_not-rev":8,"gt-lt":1},"hook_time":0.000028784,"search_time":0.000033173,"apply_time":0.000038983,"rebuild_time":5.19e-6,"total_time":0.000077588,"data":null,"n_rebuilds":0,"stop_reason":null},{"egraph_nodes":65,"egraph_classes":50,"applied":{"isabelle-add.commute":2,"isabelle-mult.commute":4,"reduce_mod_bis":4,"mod_eq":2,"mod_prop_sum":2,"sel_def":3,"not_bw_not":2},"hook_time":0.000023715,"search_time":0.000085441,"apply_time":0.000070745,"rebuild_time":6.782e-6,"total_time":0.000163149,"data":null,"n_rebuilds":4,"stop_reason":null},{"egraph_nodes":89,"egraph_classes":51,"applied":{"isabelle-add.commute":2,"mul_by_bit_eq":2,"mul_eq_prec":6,"reduce_mod_bis":1,"mod_prop_sum":4,"mod_prop_mul":2,"mod_prop_not":3,"not_bw_not-rev":2},"hook_time":0.000022472,"search_time":0.000111932,"apply_time":0.000157629,"rebuild_time":6.792e-6,"total_time":0.000276554,"data":null,"n_rebuilds":2,"stop_reason":null},{"egraph_nodes":135,"egraph_classes":73,"applied":{"isabelle-add.commute":4,"isabelle-mult.commute":5,"add_eq_prec":15,"mul_by_bit_eq":2,"mul_eq_prec":8,"reduce_mod_bis":6,"mod_prop_mul":4,"add_as_xor_and":3,"not_bw_not":3,"not_bw_not-rev":4},"hook_time":0.000028204,"search_time":0.000194427,"apply_time":0.000375379,"rebuild_time":0.000017885,"total_time":0.000587922,"data":null,"n_rebuilds":14,"stop_reason":null},{"egraph_nodes":231,"egraph_classes":101,"applied":{},"hook_time":0.00003196,"search_time":4.1e-8,"apply_time":8e-8,"rebuild_time":5.31e-6,"total_time":5.701e-6,"data":null,"n_rebuilds":0,"stop_reason":{"Other":"Found equivalence"}}]}]